downstream/get_cxl.sv

// NOTE; with current implementaton, will have to send a "fake" cancel to initiate registers 

module get_Cxl(client_id, amount, ack, clk);

  input  clk; // for now use same clock to read and write, just not at same time
  input[4:0]  client_id;
  input[31:0] amount;
  output ack;
  reg[4:0] past_client;
  reg[31:0] past_amount;
  reg new_cancel;
  assign ack = new_cancel;
  // always @(client_id, amount) begin 
  //   new_cancel <= 1;
  // end 
  always @(posedge clk)
  begin 
	  if (client_id != past_client)  new_cancel <= 1;
	  else if (amount != past_amount) new_cancel <=1; 
    else  new_cancel <= 0;
	  past_client <= client_id;
	  past_amount <= amount;  
  end
endmodule

downstream/downstream.sv
/*
 * Finite state machine.
 * IDLE -> STATE_UPDATE_MEM when ack goes high 
 * STATE_UPDATE_MEM -> IDLE when memwr goes low 
 */ 
module downstream_processor(clk, ack, memwr, out);
  input  clk;
  input ack; // how to ensure it will go back to 0?
  input memwr; // how to ensure it will go back to 0?
  output out;
  
  reg [1:0] state;

  // State encodings
  parameter [1:0]
    IDLE    = 2'b01,
    STATE_UPDATE_MEM = 2'b10;
    
  // State machine output
  assign out = (state == STATE_UPDATE_MEM);  
  // State transitions
  always @(posedge clk) begin
    case (state)
      IDLE:
        if (ack) begin
          state <= STATE_UPDATE_MEM;
        end else begin
          state <= IDLE;
        end
      STATE_UPDATE_MEM:
        if (memwr) begin
          state <= IDLE;
        end else begin
          state <= STATE_UPDATE_MEM;
        end
      default:
        state <= IDLE;
    endcase
  end

endmodule

shared/ramdownstream.sv
/* 
 * Random Access Memory (RAM) with
 * 1 read port and 1 write port (for now )
 downstream_address_write = clientID 
 data_write = value of accumulated cancelled order (32 bits)
 */
module ramdownstream (clk_write, downstream_address_write,
  data_write, downstream_write_enable,
  clk_read, address_read, data_read, memwr);
  
  parameter D_WIDTH = 32;
  parameter A_WIDTH = 5;
  parameter A_MAX = 32; // 2^A_WIDTH

  // Write port
  input                clk_write;
  input  [A_WIDTH-1:0] downstream_address_write;
  input  [D_WIDTH-1:0] data_write;
  input                downstream_write_enable;

  // Read port
  input                clk_read;
  input  [A_WIDTH-1:0] address_read;
  output [D_WIDTH-1:0] data_read;
  output               memwr; //ensures it's written
  
  reg                 memwr;
  reg    [D_WIDTH-1:0] data_read;
  
  // Memory as multi-dimensional array
  reg [D_WIDTH-1:0] memory [A_MAX-1:0];

  // initialise memory
  integer i;
  initial begin
    for (i=0;i<A_MAX;i=i+1)
      memory[i] = 32'b0;
  end

  // Write data to memory
  always @(posedge clk_write) begin
    if (downstream_write_enable==1'b1) begin
      memory[downstream_address_write] <= data_write;
      memwr <= 1'b1;
    end
    else begin 
          memwr<=1'b0;
    end 
  end

  // Read data from memory
  always @(posedge clk_read) begin
    data_read <= memory[address_read];
  end

endmodule

downstream/downstream_top.sv
/*
 * top level to call different modules in upstream
 compile with the following flags in icarus verilog:  -Wall -g2012 bc inputs/outputs fed back
 */ 

 `include "../shared/ramdownstream.sv"
 `include "downstream.sv"
 `include "get_cxl.sv"

module downstream_top( clk, client_id, amount, cancelled_orders, memwr /*to display testing*/);
  input[4:0]  client_id;
  input clk;
  input[31:0] amount;
  output [31:0] cancelled_orders;
  
  reg ack; //state machine input - should be in a @new stuff instead and manually set ack to 1 
  reg update_memory; //RAM inputs, state machine output by default 0
  output memwr; // RAM bool output & State machine input


  // instantiate downstream ram (should it be done here? )
  ramdownstream #(32, 5, 32) RAMDOWNSTREAM (
    .clk_write(clk),                            // input 
    .downstream_address_write(client_id),       // input 
    .data_write(amount+cancelled_orders),       // input[31:0]  // check that it doesn't mix for client with pipeline 
    .downstream_write_enable(update_memory),// input 
    .clk_read(clk),                             // input 
    .address_read(client_id),                   // input [4:0]
    .memwr(memwr),                              // output 
    .data_read(cancelled_orders));              // output[31:0]


  //instantiate upstream state machine to know current state 
  downstream_processor DOWNSTREAMPROCESSOR(.clk(clk),
          .ack(ack),    //input from get_cxl
          .memwr(memwr), //input from ramdownstream
          .out(update_memory)); //output for state machine


  get_Cxl get_Cxl(.clk(clk), //input
          .client_id(client_id),  // input [4:0]
          .amount(amount),  // input[31:0]
          .ack(ack));       //output 

  // always @(posedge clk)
  // begin 
  //   ack = ack;
  //   memwr = memwr; 
  // end 
endmodule

downstream/downtoptestbench.sv
// Testbench
module downtoptesttest;
  reg clk, memwr, downenable;
  reg[4:0] client_id;
  reg[31:0] amount;
  wire[31:0] cancelled_orders;
  

  // instantiate downstream ram (should it be done here? )
  // ramdownstream #(32, 5, 32) RAMDOWNSTREAM (
  //   .clk_write(clk),                            // input 
  //   .downstream_address_write(client_id),       // input 
  //   .data_write(amount),       // input[31:0]  // check that it doesn't mix for client with pipeline 
  //   .downstream_write_enable(downenable),// input 
  //   .clk_read(clk),                             // input 
  //   .address_read(client_id),                   // input [4:0]
  //   .memwr(memwr),                              // output 
  //   .data_read(amount));              // output[31:0]

  // Instantiate device under test
  downstream_top DOWNSTREAMTOP(
          .clk(clk),
          .memwr(memwr),
          .client_id(client_id),
          .amount(amount),
          .cancelled_orders(cancelled_orders));
  
  initial begin
    // Dump waves
    $dumpfile("../testbench/outputs/Module/downstreamtop.vcd");
    $dumpvars(1, downtoptesttest);

    //  initialise empty memory everywhere:
  
    clk = 0;
    amount = 32'h00000001;
    client_id = 5'h01;
    toggle_clk;

    $display("Read initial data.");
    $display("cancelled orders for client : [%0h]: %0h,  %0h",
    client_id, cancelled_orders, memwr);
    toggle_clk;

    $display("Write new data.");
    client_id = 5'h1B;
    amount = 32'h000000C5;
    toggle_clk;
    toggle_clk;
    $display("wait for state machine");
    $display("cancelled orders for client : [%0h]: %0h,  %0h",
      client_id, cancelled_orders, memwr);
    toggle_clk;
    
    $display("Write new data.");
    amount = 32'h000005C5;
    toggle_clk;
      
    $display("Read new data.");
    $display("cancelled orders for client : [%0h]: %0h,  %0h",
      client_id, cancelled_orders, memwr);
    toggle_clk;

    $display("Read new data.");
    $display("cancelled orders for client : [%0h]: %0h,  %0h",
      client_id, cancelled_orders, memwr);
      toggle_clk;

    $display("Read new data.");
    $display("cancelled orders for client : [%0h]: %0h,  %0h",
      client_id, cancelled_orders, memwr);
      toggle_clk;

    $display("Read new data.");
    $display("cancelled orders for client : [%0h]: %0h,  %0h",
      client_id, cancelled_orders, memwr);
  end
  
  task toggle_clk;
    begin
      #10 clk = ~clk;
      #10 clk = ~clk;
    end
  endtask
    
endmodule

testbench/outputs/Module/downstreamtop.vcd
$date
	Wed Nov 17 17:35:29 2021
$end
$version
	Icarus Verilog
$end
$timescale
	1s
$end
$scope module downtoptesttest $end
$var wire 1 ! memwr $end
$var wire 32 " cancelled_orders [31:0] $end
$var reg 32 # amount [31:0] $end
$var reg 5 $ client_id [4:0] $end
$var reg 1 % clk $end
$upscope $end
$enddefinitions $end
#0
$dumpvars
0%
b1 $
b1 #
bx "
x!
$end
#10
0!
b0 "
1%
#20
0%
#30
1%
#40
b11000101 #
b11011 $
0%
#50
1%
#60
0%
#70
1%
#80
0%
#90
1!
1%
#100
b10111000101 #
0%
#110
b11000101 "
1%
#120
0%
#130
0!
b10111000101 "
1%
#140
0%
#150
1!
1%
#160
0%
#170
b101110001010 "
1%
